qualitics_ai/__init__.py
qualitics_ai/__main__.py
qualitics_ai/cli.py
qualitics_ai/analysis/__init__.py
qualitics_ai/analysis/bug_analyzer.py
qualitics_ai/analysis/test_gap_analyzer.py
qualitics_ai/core/__init__.py
qualitics_ai/core/analyzer.py
qualitics_ai/core/config.py
qualitics_ai/integrations/__init__.py
qualitics_ai/integrations/bug_tracking_factory.py
qualitics_ai/integrations/repository_factory.py
qualitics_ai-1.0.0.dist-info/METADATA
qualitics_ai-1.0.0.dist-info/WHEEL
qualitics_ai-1.0.0.dist-info/entry_points.txt
qualitics_ai-1.0.0.dist-info/top_level.txt
qualitics_ai-1.0.0.dist-info/RECORD
