Metadata-Version: 2.4
Name: qualitics-ai
Version: 1.0.0
Summary: Intelligent AI agent for automated test gap analysis and quality intelligence
Author-email: Arpit Kothari <arpit@qualitics.ai>
License: Proprietary
Project-URL: Homepage, https://github.com/arpitkothari-hub/qualitics-ai
Project-URL: Documentation, https://arpitkothari-hub.github.io/qualitics-ai
Project-URL: Repository, https://github.com/arpitkothari-hub/qualitics-ai
Project-URL: Issues, https://github.com/arpitkothari-hub/qualitics-ai/issues
Keywords: ai,testing,quality-assurance,bug-analysis,test-gap-analysis
Classifier: Development Status :: 4 - Beta
Classifier: Intended Audience :: Developers
Classifier: Topic :: Software Development :: Quality Assurance
Classifier: Topic :: Software Development :: Testing
Classifier: Topic :: Scientific/Engineering :: Artificial Intelligence
Classifier: Programming Language :: Python :: 3
Classifier: Programming Language :: Python :: 3.10
Classifier: Programming Language :: Python :: 3.11
Classifier: Programming Language :: Python :: 3.12
Classifier: Operating System :: OS Independent
Requires-Python: >=3.10
Requires-Dist: aiohttp>=3.8.0
Requires-Dist: pydantic>=2.0.0
Requires-Dist: pyyaml>=6.0
Requires-Dist: click>=8.0.0
Requires-Dist: rich>=13.0.0
Requires-Dist: jinja2>=3.1.0
Requires-Dist: pandas>=2.0.0
Requires-Dist: numpy>=1.24.0
Requires-Dist: nltk>=3.8
Requires-Dist: spacy>=3.6.0
Requires-Dist: openai>=1.0.0
Requires-Dist: requests>=2.31.0
Requires-Dist: atlassian-python-api>=3.41.0
Requires-Dist: PyGithub>=1.59.0
Requires-Dist: reportlab>=4.0.0
Requires-Dist: markdown>=3.5.0
Requires-Dist: beautifulsoup4>=4.12.0
Requires-Dist: python-dotenv>=1.0.0
Requires-Dist: cryptography>=41.0.0
Requires-Dist: structlog>=23.1.0
Requires-Dist: sentry-sdk>=1.32.0
Provides-Extra: dev
Requires-Dist: pytest>=7.4.0; extra == "dev"
Requires-Dist: pytest-asyncio>=0.21.0; extra == "dev"
Requires-Dist: pytest-cov>=4.1.0; extra == "dev"
Requires-Dist: pytest-mock>=3.11.0; extra == "dev"
Requires-Dist: black>=23.7.0; extra == "dev"
Requires-Dist: flake8>=6.0.0; extra == "dev"
Requires-Dist: mypy>=1.5.0; extra == "dev"
Requires-Dist: isort>=5.12.0; extra == "dev"
Requires-Dist: pre-commit>=3.3.0; extra == "dev"
Requires-Dist: types-PyYAML>=6.0.0; extra == "dev"
Requires-Dist: types-requests>=2.31.0; extra == "dev"
Requires-Dist: types-beautifulsoup4>=4.12.0; extra == "dev"
Provides-Extra: docs
Requires-Dist: sphinx>=7.1.0; extra == "docs"
Requires-Dist: sphinx-rtd-theme>=1.3.0; extra == "docs"
